CHANGES.txt
MANIFEST.in
README.rst
setup.py
tableau/__init__.py
tableau/builder.py
tableau/containers.py
tableau/dataset.py
tableau/declarations.py
tableau/sql.py
tableau/sqla.py
tableau/tests.py
tableau/utils.py
tableau.egg-info/PKG-INFO
tableau.egg-info/SOURCES.txt
tableau.egg-info/dependency_links.txt
tableau.egg-info/top_level.txt