Metadata-Version: 1.0
Name: tableau
Version: 0.0.3
Summary: Tableau is a collection of helper classes for building test fixtures and seed data
Home-page: http://github.com/moriyoshi/tableau
Author: Moriyoshi Koizumi
Author-email: mozo@mozo.jp
License: MIT License
Keywords: test testing fixture seed
Platform: UNKNOWN
Classifier: Environment :: Other Environment
Classifier: Intended Audience :: Developers
Classifier: License :: OSI Approved :: MIT License
Classifier: Operating System :: OS Independent
Classifier: Programming Language :: Python
Classifier: Topic :: Software Development :: Testing
Classifier: Topic :: Software Development :: Quality Assurance
Classifier: Topic :: Utilities
